AnkiChinese/__init__.py
AnkiChinese/export.py
AnkiChinese/main.py
AnkiChinese/scraper.py
AnkiChinese/card_template/_CNstrokeorder.ttf
AnkiChinese/card_template/__init__.py
AnkiChinese/card_template/back.html
AnkiChinese/card_template/front.html
AnkiChinese/card_template/styles.css
AnkiChinese-1.3.8.dist-info/LICENSE.txt
AnkiChinese-1.3.8.dist-info/METADATA
AnkiChinese-1.3.8.dist-info/WHEEL
AnkiChinese-1.3.8.dist-info/entry_points.txt
AnkiChinese-1.3.8.dist-info/top_level.txt
AnkiChinese-1.3.8.dist-info/RECORD
