Metadata-Version: 2.1
Name: AnkiChinese
Version: 1.3.8
Summary: An ArchChinese scraper for Anki
Home-page: https://github.com/autoelk/AnkiChinese
Author: Luke Tao
Author-email: luketao68@gmail.com
Project-URL: Repository, https://github.com/autoelk/AnkiChinese
Project-URL: Bug Tracker, https://github.com/autoelk/AnkiChinese/issues
Project-URL: Changelog, https://github.com/autoelk/AnkiChinese/releases
Classifier: Programming Language :: Python :: 3
Classifier: License :: OSI Approved :: MIT License
Classifier: Operating System :: OS Independent
Requires-Python: >=3.8
License-File: LICENSE.txt
Requires-Dist: bs4
Requires-Dist: html5lib
Requires-Dist: aiometer
Requires-Dist: playwright
Requires-Dist: pandas
Requires-Dist: genanki
Requires-Dist: gooey
Requires-Dist: requests
Requires-Dist: ankipandas
